bunyan
tests
