Metadata-Version: 1.0
Name: bunyan
Version: 0.1.1
Summary: Bunyan python logger
Home-page: https://www.github.com/uphold/python-bunyan/
Author: Jorge Alpedrinha Ramos
Author-email: python@uphold.com
License: LICENSE
Platform: UNKNOWN
